{"moduleName":null,"summaries":[{"symbol":{"__symbol":0,"members":[]},"metadata":{"type":"string"}},{"symbol":{"__symbol":1,"members":[]},"metadata":{"type":"string"}},{"symbol":{"__symbol":2,"members":[]},"metadata":{"__symbolic":"class","extends":{"__symbol":3,"members":[]},"members":{"ChangePage1":[{"__symbolic":"method","decorators":[{"__symbolic":"call","expression":{"__symbol":4,"members":[]},"arguments":[{"name":"ChangePage1","params":{"loadCommandName":"Filter1","loadCommandFrameId":"#{root-component}"},"paramDescriptions":{"loadCommandName":{"type":"string"},"loadCommandFrameId":{"type":"string"}}}]}]}],"datagridRemove1":[{"__symbolic":"method","decorators":[{"__symbolic":"call","expression":{"__symbol":4,"members":[]},"arguments":[{"name":"datagridRemove1","params":{"id":"","refreshCommandName":"","refreshCommandFrameId":"","successMsg":""},"paramDescriptions":{"id":{"__symbol":0,"members":[]},"refreshCommandName":{"type":"string"},"refreshCommandFrameId":{"type":"string"},"successMsg":{"type":"string"}}}]}]}],"datagridEdit1":[{"__symbolic":"method","decorators":[{"__symbolic":"call","expression":{"__symbol":4,"members":[]},"arguments":[{"name":"datagridEdit1","params":{"url":"fb6d45a4-f283-4a22-a0b9-708d6f8164d7","params":"","idToEdit":"","enableRefresh":"","tabName":"","destructuring":""},"paramDescriptions":{"url":{"type":"string"},"params":{"type":"string"},"idToEdit":{"type":"string"},"enableRefresh":{"type":"string"},"tabName":{"type":"string"},"destructuring":{"type":"string"}}}]}]}],"datagridRemove2":[{"__symbolic":"method","decorators":[{"__symbolic":"call","expression":{"__symbol":4,"members":[]},"arguments":[{"name":"datagridRemove2","params":{"id":"{DATA~/#{root-component}/id}","refreshCommandName":"Load1","refreshCommandFrameId":"#{data-grid-component}","successMsg":""},"paramDescriptions":{"id":{"__symbol":1,"members":[]},"refreshCommandName":{"type":"string"},"refreshCommandFrameId":{"type":"string"},"successMsg":{"type":"string"}}}]}]}],"datagridEdit2":[{"__symbolic":"method","decorators":[{"__symbolic":"call","expression":{"__symbol":4,"members":[]},"arguments":[{"name":"datagridEdit2","params":{"url":"fb6d45a4-f283-4a22-a0b9-708d6f8164d7","params":"{\"action\":\"LoadAndEdit1\", \"id\":\"{DATA~/#{data-grid-component}/id}\"}","idToEdit":"","enableRefresh":"","tabName":"","destructuring":""},"paramDescriptions":{"url":{"type":"string"},"params":{"type":"string"},"idToEdit":{"type":"string"},"enableRefresh":{"type":"string"},"tabName":{"type":"string"},"destructuring":{"type":"string"}}}]}]}],"datagridChangePage1":[{"__symbolic":"method","decorators":[{"__symbolic":"call","expression":{"__symbol":4,"members":[]},"arguments":[{"name":"datagridChangePage1","params":{"loadCommandName":"Filter1","loadCommandFrameId":"#{root-component}"},"paramDescriptions":{"loadCommandName":{"type":"string"},"loadCommandFrameId":{"type":"string"}}}]}]}],"datagridChangePage2":[{"__symbolic":"method","decorators":[{"__symbolic":"call","expression":{"__symbol":4,"members":[]},"arguments":[{"name":"datagridChangePage2","params":{"loadCommandName":"Filter1","loadCommandFrameId":"#{root-component}"},"paramDescriptions":{"loadCommandName":{"type":"string"},"loadCommandFrameId":{"type":"string"}}}]}]}]}},"type":{"summaryKind":3,"type":{"reference":{"__symbol":2,"members":[]},"diDeps":[],"lifecycleHooks":[1]}}}],"symbols":[{"__symbol":0,"name":"ɵ0","filePath":"./datagridcomponentviewmodel"},{"__symbol":1,"name":"ɵ1","filePath":"./datagridcomponentviewmodel"},{"__symbol":2,"name":"DataGridComponentViewmodel","filePath":"./datagridcomponentviewmodel"},{"__symbol":3,"name":"ViewModel","filePath":"@farris/devkit"},{"__symbol":4,"name":"NgCommand","filePath":"@farris/devkit"}]}