{"moduleName":null,"summaries":[{"symbol":{"__symbol":0,"members":[]},"metadata":{"__symbolic":"class","extends":{"__symbol":1,"members":[]},"members":{"teacher_id":[{"__symbolic":"property","decorators":[{"__symbolic":"call","expression":{"__symbol":2,"members":[]},"arguments":[{"id":"teacher_id_16fb257e_h2az","name":"{{teacher_id_16fb257e_h2az}}","binding":"teacher_id","updateOn":"blur","defaultI18nValue":"教师工号","validRules":[{"type":"required","constraints":[true]},{"type":"matches","constraints":[""]}]}]}]}],"name":[{"__symbolic":"property","decorators":[{"__symbolic":"call","expression":{"__symbol":2,"members":[]},"arguments":[{"id":"name_a9df9e1e_xgj5","name":"{{name_a9df9e1e_xgj5}}","binding":"name","updateOn":"blur","defaultI18nValue":"教师姓名","validRules":[{"type":"required","constraints":[true]}]}]}]}],"department":[{"__symbolic":"property","decorators":[{"__symbolic":"call","expression":{"__symbol":2,"members":[]},"arguments":[{"id":"department_6a312a92_bvcd","name":"{{department_6a312a92_bvcd}}","binding":"department","updateOn":"change","defaultI18nValue":"所在院系"}]}]}],"password":[{"__symbolic":"property","decorators":[{"__symbolic":"call","expression":{"__symbol":2,"members":[]},"arguments":[{"id":"password_2e41f9ab_xzbn","name":"{{password_2e41f9ab_xzbn}}","binding":"password","updateOn":"blur","defaultI18nValue":"密码","validRules":[{"type":"required","constraints":[true]},{"type":"matches","constraints":[""]}]}]}]}],"email_Email":[{"__symbolic":"property","decorators":[{"__symbolic":"call","expression":{"__symbol":2,"members":[]},"arguments":[{"id":"email_Email_c4dc35f2_i5zn","name":"{{email_Email_c4dc35f2_i5zn}}","binding":"email.email","updateOn":"blur","defaultI18nValue":"邮箱","validRules":[{"type":"matches","constraints":[""]}]}]}]}]}},"type":{"summaryKind":3,"type":{"reference":{"__symbol":0,"members":[]},"diDeps":[],"lifecycleHooks":[1]}}}],"symbols":[{"__symbol":0,"name":"BasicFormViewmodelForm","filePath":"./basicformviewmodelform"},{"__symbol":1,"name":"Form","filePath":"@farris/devkit"},{"__symbol":2,"name":"NgFormControl","filePath":"@farris/devkit"}]}